dependify/__init__.py
dependify/container.py
dependify/context.py
dependify/decorators.py
dependify/dependency.py
dependify-1.1.0.dist-info/licenses/LICENSE
dependify-1.1.0.dist-info/METADATA
dependify-1.1.0.dist-info/WHEEL
dependify-1.1.0.dist-info/top_level.txt
dependify-1.1.0.dist-info/RECORD
