Metadata-Version: 2.4
Name: dependify
Version: 1.1.0
Summary: Dependency injection package
Author-email: Kenneth Ulloa <ulloakenth@gmail.com>
Project-URL: Homepage, https://github.com/KennethUlloa/dependify
Classifier: Programming Language :: Python :: 3
Classifier: License :: OSI Approved :: MIT License
Classifier: Operating System :: OS Independent
Requires-Python: >=3.10
License-File: LICENSE
Dynamic: license-file
